ezcolors/Colors.py
ezcolors/__init__.py
ezcolors/names.json
ezcolors/palettes.py
ezcolors/utilities.py
ezcolors/web.json
ezcolors-1.0.7.dist-info/LICENSE
ezcolors-1.0.7.dist-info/METADATA
ezcolors-1.0.7.dist-info/WHEEL
ezcolors-1.0.7.dist-info/top_level.txt
ezcolors-1.0.7.dist-info/RECORD
